Metadata-Version: 2.1
Name: curatedmetagenomicspipeline
Version: 0.0.4
Summary: UNKNOWN
Home-page: https://github.com/waldronlab/curatedmetagenomics
Author: Francesco Beghini
Author-email: francesco.beghini@unitn.it
License: UNKNOWN
Platform: UNKNOWN
